act_operator/__init__.py
act_operator/__main__.py
act_operator/cli.py
act_operator/utils.py
act_operator/version.py
act_operator/scaffold/__init__.py
act_operator/scaffold/cookiecutter.json
act_operator/scaffold/{{ cookiecutter.act_slug }}/.env.example
act_operator/scaffold/{{ cookiecutter.act_slug }}/.gitignore
act_operator/scaffold/{{ cookiecutter.act_slug }}/.pre-commit-config.yaml
act_operator/scaffold/{{ cookiecutter.act_slug }}/README.md
act_operator/scaffold/{{ cookiecutter.act_slug }}/TEMPLATE_README.md
act_operator/scaffold/{{ cookiecutter.act_slug }}/drawkit_en.xml
act_operator/scaffold/{{ cookiecutter.act_slug }}/drawkit_kr.xml
act_operator/scaffold/{{ cookiecutter.act_slug }}/langgraph.json
act_operator/scaffold/{{ cookiecutter.act_slug }}/pyproject.toml
act_operator/scaffold/{{ cookiecutter.act_slug }}/.claude/skills/architecting-act/SKILL.md
act_operator/scaffold/{{ cookiecutter.act_slug }}/.claude/skills/architecting-act/resources/agentic-design-patterns.md
act_operator/scaffold/{{ cookiecutter.act_slug }}/.claude/skills/architecting-act/resources/cast-analysis-guide.md
act_operator/scaffold/{{ cookiecutter.act_slug }}/.claude/skills/architecting-act/resources/pattern-decision-matrix.md
act_operator/scaffold/{{ cookiecutter.act_slug }}/.claude/skills/architecting-act/resources/design/edge-routing.md
act_operator/scaffold/{{ cookiecutter.act_slug }}/.claude/skills/architecting-act/resources/design/node-specification.md
act_operator/scaffold/{{ cookiecutter.act_slug }}/.claude/skills/architecting-act/resources/design/state-schema.md
act_operator/scaffold/{{ cookiecutter.act_slug }}/.claude/skills/architecting-act/resources/modes/add-cast-questions.md
act_operator/scaffold/{{ cookiecutter.act_slug }}/.claude/skills/architecting-act/resources/modes/extract-subcast-questions.md
act_operator/scaffold/{{ cookiecutter.act_slug }}/.claude/skills/architecting-act/resources/modes/initial-design-questions.md
act_operator-0.2.4.dist-info/METADATA
act_operator-0.2.4.dist-info/WHEEL
act_operator-0.2.4.dist-info/entry_points.txt
act_operator-0.2.4.dist-info/licenses/LICENSE
act_operator-0.2.4.dist-info/RECORD
