Metadata-Version: 2.4
Name: act-operator
Version: 0.2.4
Summary: Proact0’s CLI for bootstrapping LangGraph-based “Act - AX Template” blueprints.
Project-URL: Repository, https://github.com/Proact0/act-operator
Project-URL: Homepage, https://github.com/Proact0/Act-Operator
Author: Joongheon Park
License-Expression: Apache-2.0
License-File: LICENSE
Requires-Python: >=3.11
Requires-Dist: cookiecutter>=2.6.0
Requires-Dist: rich>=14.1.0
Requires-Dist: typer>=0.19.2
